mlconf/__init__.py
mlconf-0.0.6.dist-info/LICENSE.txt
mlconf-0.0.6.dist-info/METADATA
mlconf-0.0.6.dist-info/WHEEL
mlconf-0.0.6.dist-info/top_level.txt
mlconf-0.0.6.dist-info/RECORD
