Metadata-Version: 2.1
Name: mlconf
Version: 0.0.6
Summary: UNKNOWN
Home-page: https://github.com/andreasgrv/mlconf
Author: Andreas Grivas
Author-email: andreasgrv@gmail.com
License: BSD
Download-URL: https://github.com/andreasgrv/mlconf/archive/0.0.6.tar.gz
Keywords: config argparse yaml machine-learning
Platform: UNKNOWN
Classifier: Development Status :: 3 - Alpha
Classifier: Intended Audience :: Developers
Classifier: License :: OSI Approved :: BSD License
Classifier: Programming Language :: Python :: 3
Classifier: Programming Language :: Python :: 3.6
Classifier: Programming Language :: Python :: 3.7
Classifier: Programming Language :: Python :: 3.8
Requires-Dist: argparse
Requires-Dist: pyyaml
